[
  { "id": "be", "name": "Belgium",                "flag": "🇧🇪", "budget": "low",  "distance": "regional", "near": ["northwest", "british"],           "vibes": ["culture", "food"],                                    "seasons": ["spring", "summer", "autumn"],           "party": ["couple", "group"], "favorite": false, "enabled": true },
  { "id": "nl", "name": "Netherlands",            "flag": "🇳🇱", "budget": "mid",  "distance": "regional", "near": ["northwest", "british"],           "vibes": ["culture", "nature", "nightlife"],                     "seasons": ["spring", "summer"],                     "party": ["couple", "group"], "favorite": false, "enabled": true },
  { "id": "de", "name": "Germany",                "flag": "🇩🇪", "budget": "mid",  "distance": "regional", "near": ["northwest", "central", "nordic"], "vibes": ["culture", "nature", "winter"],                        "seasons": ["spring", "summer", "autumn", "winter"], "party": ["couple", "group"], "favorite": false, "enabled": true },
  { "id": "fr", "name": "France",                 "flag": "🇫🇷", "budget": "mid",  "distance": "regional", "near": ["northwest", "british", "south"],  "vibes": ["culture", "food", "nature", "beach"],                 "seasons": ["spring", "summer", "autumn"],           "party": ["couple", "group"], "favorite": false, "enabled": true },
  { "id": "lu", "name": "Luxembourg",             "flag": "🇱🇺", "budget": "mid",  "distance": "regional", "near": ["northwest"],                      "vibes": ["nature", "culture"],                                  "seasons": ["spring", "summer", "autumn"],           "party": ["couple"], "favorite": false, "enabled": true },
  { "id": "gb", "name": "United Kingdom",         "flag": "🇬🇧", "budget": "high", "distance": "regional", "near": ["northwest", "british"],           "vibes": ["culture", "nature", "food", "nightlife"],             "seasons": ["spring", "summer", "autumn"],           "party": ["couple", "group"], "favorite": true, "enabled": true },
  { "id": "dk", "name": "Denmark",                "flag": "🇩🇰", "budget": "high", "distance": "regional", "near": ["northwest", "nordic"],            "vibes": ["culture", "food"],                                    "seasons": ["spring", "summer"],                     "party": ["couple", "group"], "favorite": true, "enabled": true },

  { "id": "ie", "name": "Ireland",                "flag": "🇮🇪", "budget": "mid",  "distance": "europe",   "near": ["british"],                        "vibes": ["nature", "culture", "food"],                          "seasons": ["spring", "summer", "autumn"],           "party": ["couple", "group"], "favorite": true, "enabled": true },
  { "id": "no", "name": "Norway",                 "flag": "🇳🇴", "budget": "high", "distance": "europe",   "near": ["nordic"],                         "vibes": ["nature", "winter", "adventure"],                      "seasons": ["summer", "winter"],                     "party": ["couple", "group"], "favorite": true, "enabled": true },
  { "id": "se", "name": "Sweden",                 "flag": "🇸🇪", "budget": "high", "distance": "europe",   "near": ["nordic"],                         "vibes": ["nature", "culture", "winter"],                        "seasons": ["spring", "summer", "winter"],           "party": ["couple", "group"], "favorite": true, "enabled": true },
  { "id": "fi", "name": "Finland",                "flag": "🇫🇮", "budget": "high", "distance": "europe",   "near": ["nordic"],                         "vibes": ["nature", "winter", "wellness"],                       "seasons": ["summer", "winter"],                     "party": ["couple", "group"], "favorite": true, "enabled": true },
  { "id": "is", "name": "Iceland",                "flag": "🇮🇸", "budget": "high", "distance": "europe",   "near": [],                                 "vibes": ["nature", "winter", "adventure", "wellness"],          "seasons": ["summer", "winter"],                     "party": ["couple"], "favorite": false, "enabled": true },
  { "id": "ee", "name": "Estonia",                "flag": "🇪🇪", "budget": "mid",  "distance": "europe",   "near": ["nordic"],                         "vibes": ["culture", "nature"],                                  "seasons": ["spring", "summer"],                     "party": ["couple", "group"], "favorite": false, "enabled": true },
  { "id": "lv", "name": "Latvia",                 "flag": "🇱🇻", "budget": "low",  "distance": "europe",   "near": ["nordic"],                         "vibes": ["culture", "nature", "nightlife"],                     "seasons": ["spring", "summer"],                     "party": ["couple", "group"], "favorite": false, "enabled": false },
  { "id": "lt", "name": "Lithuania",              "flag": "🇱🇹", "budget": "low",  "distance": "europe",   "near": ["nordic"],                         "vibes": ["culture", "nature"],                                  "seasons": ["spring", "summer", "autumn"],           "party": ["couple", "group"], "favorite": false, "enabled": false },
  { "id": "at", "name": "Austria",                "flag": "🇦🇹", "budget": "mid",  "distance": "europe",   "near": ["central"],                        "vibes": ["nature", "culture", "winter", "adventure"],           "seasons": ["summer", "winter"],                     "party": ["couple", "group"], "favorite": false, "enabled": true },
  { "id": "ch", "name": "Switzerland",            "flag": "🇨🇭", "budget": "high", "distance": "europe",   "near": ["central", "south"],               "vibes": ["nature", "winter", "adventure"],                      "seasons": ["summer", "winter"],                     "party": ["couple"], "favorite": false, "enabled": true },
  { "id": "sk", "name": "Slovakia",               "flag": "🇸🇰", "budget": "low",  "distance": "europe",   "near": ["central"],                        "vibes": ["nature", "adventure", "winter"],                      "seasons": ["summer", "winter"],                     "party": ["couple", "group"], "favorite": false, "enabled": true },
  { "id": "it", "name": "Italy",                  "flag": "🇮🇹", "budget": "mid",  "distance": "europe",   "near": ["south", "central"],               "vibes": ["culture", "food", "nature", "beach"],                 "seasons": ["spring", "summer", "autumn"],           "party": ["couple", "group"], "favorite": false, "enabled": true },
  { "id": "es", "name": "Spain",                  "flag": "🇪🇸", "budget": "mid",  "distance": "europe",   "near": ["south"],                          "vibes": ["culture", "food", "beach", "nightlife"],              "seasons": ["spring", "summer", "autumn"],           "party": ["couple", "group"], "favorite": false, "enabled": true },
  { "id": "pt", "name": "Portugal",               "flag": "🇵🇹", "budget": "mid",  "distance": "europe",   "near": ["south"],                          "vibes": ["culture", "food", "nature", "beach"],                 "seasons": ["spring", "summer", "autumn"],           "party": ["couple", "group"], "favorite": false, "enabled": true },
  { "id": "gr", "name": "Greece",                 "flag": "🇬🇷", "budget": "mid",  "distance": "europe",   "near": ["south"],                          "vibes": ["culture", "nature", "beach"],                         "seasons": ["spring", "summer", "autumn"],           "party": ["couple", "group"], "favorite": false, "enabled": true },
  { "id": "mt", "name": "Malta",                  "flag": "🇲🇹", "budget": "mid",  "distance": "europe",   "near": ["south"],                          "vibes": ["culture", "beach", "nightlife"],                      "seasons": ["spring", "summer", "autumn"],           "party": ["couple", "group"], "favorite": false, "enabled": true },
  { "id": "cy", "name": "Cyprus",                 "flag": "🇨🇾", "budget": "mid",  "distance": "europe",   "near": [],                                 "vibes": ["beach", "culture", "food"],                           "seasons": ["spring", "summer", "autumn"],           "party": ["couple", "group"], "favorite": false, "enabled": false },
  { "id": "si", "name": "Slovenia",               "flag": "🇸🇮", "budget": "mid",  "distance": "europe",   "near": ["central", "south"],               "vibes": ["nature", "food", "adventure"],                        "seasons": ["spring", "summer", "autumn"],           "party": ["couple"], "favorite": false, "enabled": true },
  { "id": "cz", "name": "Czechia",                "flag": "🇨🇿", "budget": "low",  "distance": "europe",   "near": ["central"],                        "vibes": ["culture", "food"],                                    "seasons": ["spring", "summer", "autumn", "winter"], "party": ["couple", "group"], "favorite": false, "enabled": true },
  { "id": "pl", "name": "Poland",                 "flag": "🇵🇱", "budget": "low",  "distance": "europe",   "near": ["central"],                        "vibes": ["culture", "nature"],                                  "seasons": ["spring", "summer", "autumn"],           "party": ["couple", "group"], "favorite": false, "enabled": true },
  { "id": "hu", "name": "Hungary",                "flag": "🇭🇺", "budget": "low",  "distance": "europe",   "near": ["central"],                        "vibes": ["culture", "food", "wellness"],                        "seasons": ["spring", "summer", "autumn"],           "party": ["couple", "group"], "favorite": false, "enabled": true },
  { "id": "ro", "name": "Romania",                "flag": "🇷🇴", "budget": "low",  "distance": "europe",   "near": ["central"],                        "vibes": ["nature", "culture", "adventure"],                     "seasons": ["spring", "summer", "autumn"],           "party": ["couple", "group"], "favorite": false, "enabled": true },
  { "id": "bg", "name": "Bulgaria",               "flag": "🇧🇬", "budget": "low",  "distance": "europe",   "near": ["central"],                        "vibes": ["beach", "nature", "winter"],                          "seasons": ["summer", "winter"],                     "party": ["couple", "group"], "favorite": false, "enabled": true },
  { "id": "hr", "name": "Croatia",                "flag": "🇭🇷", "budget": "mid",  "distance": "europe",   "near": ["south", "central"],               "vibes": ["nature", "culture", "beach"],                         "seasons": ["spring", "summer", "autumn"],           "party": ["couple", "group"], "favorite": false, "enabled": true },
  { "id": "me", "name": "Montenegro",             "flag": "🇲🇪", "budget": "low",  "distance": "europe",   "near": ["south"],                          "vibes": ["nature", "beach", "adventure"],                       "seasons": ["spring", "summer", "autumn"],           "party": ["couple", "group"], "favorite": false, "enabled": true },
  { "id": "al", "name": "Albania",                "flag": "🇦🇱", "budget": "low",  "distance": "europe",   "near": ["south"],                          "vibes": ["beach", "nature", "food"],                            "seasons": ["spring", "summer", "autumn"],           "party": ["couple", "group"], "favorite": false, "enabled": true },
  { "id": "tr", "name": "Türkiye",                "flag": "🇹🇷", "budget": "low",  "distance": "europe",   "near": [],                                 "vibes": ["culture", "food", "beach"],                           "seasons": ["spring", "summer", "autumn"],           "party": ["couple", "group"], "favorite": false, "enabled": true },
  { "id": "ge", "name": "Georgia",                "flag": "🇬🇪", "budget": "low",  "distance": "europe",   "near": [],                                 "vibes": ["nature", "food", "culture", "adventure"],             "seasons": ["spring", "summer", "autumn"],           "party": ["couple", "group"], "favorite": false, "enabled": true },
  { "id": "ma", "name": "Morocco",                "flag": "🇲🇦", "budget": "low",  "distance": "europe",   "near": ["south"],                          "vibes": ["culture", "food", "adventure", "wellness"],           "seasons": ["spring", "autumn", "winter"],           "party": ["couple", "group"], "favorite": false, "enabled": true },
  { "id": "tn", "name": "Tunisia",                "flag": "🇹🇳", "budget": "low",  "distance": "europe",   "near": [],                                 "vibes": ["beach", "culture", "food"],                           "seasons": ["spring", "summer", "autumn"],           "party": ["couple", "group"], "favorite": false, "enabled": false },
  { "id": "eg", "name": "Egypt",                  "flag": "🇪🇬", "budget": "low",  "distance": "europe",   "near": [],                                 "vibes": ["culture", "beach", "adventure"],                      "seasons": ["autumn", "winter", "spring"],           "party": ["couple", "group"], "favorite": false, "enabled": true },
  { "id": "jo", "name": "Jordan",                 "flag": "🇯🇴", "budget": "mid",  "distance": "europe",   "near": [],                                 "vibes": ["culture", "nature", "adventure"],                     "seasons": ["spring", "autumn"],                     "party": ["couple", "group"], "favorite": false, "enabled": true },
  { "id": "ba", "name": "Bosnia and Herzegovina", "flag": "🇧🇦", "budget": "low",  "distance": "europe",   "near": ["central", "south"],               "vibes": ["nature", "culture", "food"],                          "seasons": ["spring", "summer", "autumn"],           "party": ["couple", "group"], "favorite": false, "enabled": true },
  { "id": "rs", "name": "Serbia",                 "flag": "🇷🇸", "budget": "low",  "distance": "europe",   "near": ["central"],                        "vibes": ["culture", "nightlife", "food"],                       "seasons": ["spring", "summer", "autumn"],           "party": ["couple", "group"], "favorite": false, "enabled": false },
  { "id": "mk", "name": "North Macedonia",        "flag": "🇲🇰", "budget": "low",  "distance": "europe",   "near": ["south"],                          "vibes": ["nature", "culture", "food"],                          "seasons": ["spring", "summer", "autumn"],           "party": ["couple", "group"], "favorite": false, "enabled": false },
  { "id": "am", "name": "Armenia",                "flag": "🇦🇲", "budget": "low",  "distance": "europe",   "near": [],                                 "vibes": ["culture", "nature", "food"],                          "seasons": ["spring", "summer", "autumn"],           "party": ["couple", "group"], "favorite": false, "enabled": false },

  { "id": "ca", "name": "Canada",                 "flag": "🇨🇦", "budget": "high", "distance": "longhaul", "near": [],                                 "vibes": ["nature", "culture", "winter", "adventure"],           "seasons": ["summer", "autumn", "winter"],           "party": ["couple", "group"], "favorite": true, "enabled": true },
  { "id": "us", "name": "United States",          "flag": "🇺🇸", "budget": "high", "distance": "longhaul", "near": [],                                 "vibes": ["culture", "nature", "adventure", "nightlife"],        "seasons": ["spring", "summer", "autumn"],           "party": ["couple", "group"], "favorite": false, "enabled": true },
  { "id": "mx", "name": "Mexico",                 "flag": "🇲🇽", "budget": "mid",  "distance": "longhaul", "near": [],                                 "vibes": ["food", "culture", "nature", "beach"],                 "seasons": ["winter", "spring"],                     "party": ["couple", "group"], "favorite": false, "enabled": true },
  { "id": "cu", "name": "Cuba",                   "flag": "🇨🇺", "budget": "low",  "distance": "longhaul", "near": [],                                 "vibes": ["culture", "beach", "nightlife"],                      "seasons": ["winter", "spring"],                     "party": ["couple", "group"], "favorite": false, "enabled": true },
  { "id": "cr", "name": "Costa Rica",             "flag": "🇨🇷", "budget": "mid",  "distance": "longhaul", "near": [],                                 "vibes": ["nature", "beach", "adventure"],                       "seasons": ["winter", "spring"],                     "party": ["couple"], "favorite": false, "enabled": true },
  { "id": "co", "name": "Colombia",               "flag": "🇨🇴", "budget": "low",  "distance": "longhaul", "near": [],                                 "vibes": ["culture", "nature", "food", "nightlife"],             "seasons": ["winter", "spring"],                     "party": ["couple", "group"], "favorite": false, "enabled": true },
  { "id": "pe", "name": "Peru",                   "flag": "🇵🇪", "budget": "mid",  "distance": "longhaul", "near": [],                                 "vibes": ["nature", "culture", "food", "adventure"],             "seasons": ["spring", "summer"],                     "party": ["couple", "group"], "favorite": false, "enabled": true },
  { "id": "br", "name": "Brazil",                 "flag": "🇧🇷", "budget": "mid",  "distance": "longhaul", "near": [],                                 "vibes": ["beach", "nature", "nightlife", "adventure"],          "seasons": ["winter", "spring"],                     "party": ["couple", "group"], "favorite": false, "enabled": true },
  { "id": "ar", "name": "Argentina",              "flag": "🇦🇷", "budget": "mid",  "distance": "longhaul", "near": [],                                 "vibes": ["nature", "food", "culture", "adventure"],             "seasons": ["autumn", "winter", "spring"],           "party": ["couple", "group"], "favorite": false, "enabled": true },
  { "id": "za", "name": "South Africa",           "flag": "🇿🇦", "budget": "mid",  "distance": "longhaul", "near": [],                                 "vibes": ["nature", "food", "culture", "adventure"],             "seasons": ["autumn", "winter", "spring"],           "party": ["couple", "group"], "favorite": true, "enabled": true },
  { "id": "bw", "name": "Botswana",               "flag": "🇧🇼", "budget": "high", "distance": "longhaul", "near": [],                                 "vibes": ["nature", "adventure"],                                "seasons": ["summer", "autumn"],                     "party": ["couple", "group"], "favorite": false, "enabled": false },
  { "id": "tz", "name": "Tanzania",               "flag": "🇹🇿", "budget": "high", "distance": "longhaul", "near": [],                                 "vibes": ["nature", "adventure", "beach"],                       "seasons": ["summer", "autumn", "winter"],           "party": ["couple", "group"], "favorite": false, "enabled": true },
  { "id": "ke", "name": "Kenya",                  "flag": "🇰🇪", "budget": "high", "distance": "longhaul", "near": [],                                 "vibes": ["nature", "adventure", "beach"],                       "seasons": ["summer", "winter"],                     "party": ["couple", "group"], "favorite": false, "enabled": true },
  { "id": "ae", "name": "United Arab Emirates",   "flag": "🇦🇪", "budget": "high", "distance": "longhaul", "near": [],                                 "vibes": ["beach", "nightlife", "wellness"],                     "seasons": ["autumn", "winter", "spring"],           "party": ["couple", "group"], "favorite": false, "enabled": true },
  { "id": "om", "name": "Oman",                   "flag": "🇴🇲", "budget": "mid",  "distance": "longhaul", "near": [],                                 "vibes": ["nature", "culture", "adventure"],                     "seasons": ["autumn", "winter", "spring"],           "party": ["couple", "group"], "favorite": false, "enabled": false },
  { "id": "in", "name": "India",                  "flag": "🇮🇳", "budget": "low",  "distance": "longhaul", "near": [],                                 "vibes": ["culture", "food", "nature", "wellness", "adventure"], "seasons": ["autumn", "winter", "spring"],           "party": ["couple", "group"], "favorite": false, "enabled": true },
  { "id": "lk", "name": "Sri Lanka",              "flag": "🇱🇰", "budget": "low",  "distance": "longhaul", "near": [],                                 "vibes": ["beach", "nature", "culture", "food"],                 "seasons": ["winter", "spring"],                     "party": ["couple", "group"], "favorite": false, "enabled": true },
  { "id": "mv", "name": "Maldives",               "flag": "🇲🇻", "budget": "high", "distance": "longhaul", "near": [],                                 "vibes": ["beach", "wellness"],                                  "seasons": ["winter", "spring"],                     "party": ["couple"], "favorite": false, "enabled": true },
  { "id": "th", "name": "Thailand",               "flag": "🇹🇭", "budget": "low",  "distance": "longhaul", "near": [],                                 "vibes": ["food", "nature", "culture", "beach", "wellness"],     "seasons": ["winter", "spring"],                     "party": ["couple", "group"], "favorite": false, "enabled": true },
  { "id": "vn", "name": "Vietnam",                "flag": "🇻🇳", "budget": "low",  "distance": "longhaul", "near": [],                                 "vibes": ["food", "nature", "culture", "beach"],                 "seasons": ["winter", "spring"],                     "party": ["couple", "group"], "favorite": false, "enabled": true },
  { "id": "kh", "name": "Cambodia",               "flag": "🇰🇭", "budget": "low",  "distance": "longhaul", "near": [],                                 "vibes": ["culture", "nature", "food"],                          "seasons": ["winter", "spring"],                     "party": ["couple", "group"], "favorite": false, "enabled": false },
  { "id": "my", "name": "Malaysia",               "flag": "🇲🇾", "budget": "low",  "distance": "longhaul", "near": [],                                 "vibes": ["food", "nature", "culture", "beach"],                 "seasons": ["winter", "spring", "summer"],           "party": ["couple", "group"], "favorite": false, "enabled": false },
  { "id": "id", "name": "Indonesia",              "flag": "🇮🇩", "budget": "low",  "distance": "longhaul", "near": [],                                 "vibes": ["beach", "nature", "culture", "wellness"],             "seasons": ["spring", "summer", "autumn"],           "party": ["couple", "group"], "favorite": false, "enabled": true },
  { "id": "ph", "name": "Philippines",            "flag": "🇵🇭", "budget": "low",  "distance": "longhaul", "near": [],                                 "vibes": ["beach", "nature", "adventure"],                       "seasons": ["winter", "spring"],                     "party": ["couple", "group"], "favorite": false, "enabled": true },
  { "id": "kr", "name": "South Korea",            "flag": "🇰🇷", "budget": "mid",  "distance": "longhaul", "near": [],                                 "vibes": ["culture", "food", "nightlife", "nature"],             "seasons": ["spring", "autumn"],                     "party": ["couple", "group"], "favorite": false, "enabled": true },
  { "id": "jp", "name": "Japan",                  "flag": "🇯🇵", "budget": "high", "distance": "longhaul", "near": [],                                 "vibes": ["culture", "food", "nature", "winter", "wellness"],    "seasons": ["spring", "autumn", "winter"],           "party": ["couple", "group"], "favorite": false, "enabled": true },
  { "id": "au", "name": "Australia",              "flag": "🇦🇺", "budget": "high", "distance": "longhaul", "near": [],                                 "vibes": ["nature", "culture", "food", "beach", "adventure"],    "seasons": ["winter", "spring", "autumn"],           "party": ["couple", "group"], "favorite": false, "enabled": true },
  { "id": "nz", "name": "New Zealand",            "flag": "🇳🇿", "budget": "high", "distance": "longhaul", "near": [],                                 "vibes": ["nature", "culture", "adventure"],                     "seasons": ["winter", "spring", "autumn"],           "party": ["couple"], "favorite": true, "enabled": true },
  { "id": "cl", "name": "Chile",                  "flag": "🇨🇱", "budget": "mid",  "distance": "longhaul", "near": [],                                 "vibes": ["nature", "adventure", "food"],                        "seasons": ["autumn", "winter", "spring"],           "party": ["couple", "group"], "favorite": false, "enabled": true },
  { "id": "ec", "name": "Ecuador",                "flag": "🇪🇨", "budget": "mid",  "distance": "longhaul", "near": [],                                 "vibes": ["nature", "adventure"],                                "seasons": ["spring", "summer", "autumn"],           "party": ["couple", "group"], "favorite": false, "enabled": false },
  { "id": "pa", "name": "Panama",                 "flag": "🇵🇦", "budget": "mid",  "distance": "longhaul", "near": [],                                 "vibes": ["beach", "nature"],                                    "seasons": ["winter", "spring"],                     "party": ["couple", "group"], "favorite": false, "enabled": false },
  { "id": "do", "name": "Dominican Republic",     "flag": "🇩🇴", "budget": "mid",  "distance": "longhaul", "near": [],                                 "vibes": ["beach", "wellness", "nature"],                        "seasons": ["winter", "spring"],                     "party": ["couple", "group"], "favorite": false, "enabled": true },
  { "id": "cw", "name": "Curaçao",                "flag": "🇨🇼", "budget": "mid",  "distance": "longhaul", "near": [],                                 "vibes": ["beach", "nightlife"],                                 "seasons": ["autumn", "winter", "spring"],           "party": ["couple", "group"], "favorite": false, "enabled": true },
  { "id": "aw", "name": "Aruba",                  "flag": "🇦🇼", "budget": "high", "distance": "longhaul", "near": [],                                 "vibes": ["beach", "wellness"],                                  "seasons": ["autumn", "winter", "spring"],           "party": ["couple"], "favorite": false, "enabled": false },
  { "id": "cv", "name": "Cape Verde",             "flag": "🇨🇻", "budget": "mid",  "distance": "longhaul", "near": [],                                 "vibes": ["beach", "nature", "adventure"],                       "seasons": ["autumn", "winter", "spring"],           "party": ["couple", "group"], "favorite": false, "enabled": true },
  { "id": "mu", "name": "Mauritius",              "flag": "🇲🇺", "budget": "high", "distance": "longhaul", "near": [],                                 "vibes": ["beach", "nature", "wellness"],                        "seasons": ["autumn", "winter", "spring"],           "party": ["couple"], "favorite": false, "enabled": true },
  { "id": "sc", "name": "Seychelles",             "flag": "🇸🇨", "budget": "high", "distance": "longhaul", "near": [],                                 "vibes": ["beach", "wellness"],                                  "seasons": ["spring", "autumn"],                     "party": ["couple"], "favorite": false, "enabled": false },
  { "id": "na", "name": "Namibia",                "flag": "🇳🇦", "budget": "mid",  "distance": "longhaul", "near": [],                                 "vibes": ["nature", "adventure"],                                "seasons": ["autumn", "winter", "spring"],           "party": ["couple", "group"], "favorite": false, "enabled": true },
  { "id": "np", "name": "Nepal",                  "flag": "🇳🇵", "budget": "low",  "distance": "longhaul", "near": [],                                 "vibes": ["nature", "adventure", "culture"],                     "seasons": ["spring", "autumn"],                     "party": ["couple", "group"], "favorite": false, "enabled": true },
  { "id": "sg", "name": "Singapore",              "flag": "🇸🇬", "budget": "high", "distance": "longhaul", "near": [],                                 "vibes": ["food", "culture", "nightlife"],                       "seasons": ["spring", "autumn", "winter"],           "party": ["couple", "group"], "favorite": false, "enabled": true },
  { "id": "tw", "name": "Taiwan",                 "flag": "🇹🇼", "budget": "mid",  "distance": "longhaul", "near": [],                                 "vibes": ["food", "culture", "nature"],                          "seasons": ["spring", "autumn"],                     "party": ["couple", "group"], "favorite": false, "enabled": false },
  { "id": "uz", "name": "Uzbekistan",             "flag": "🇺🇿", "budget": "low",  "distance": "longhaul", "near": [],                                 "vibes": ["culture", "food"],                                    "seasons": ["spring", "autumn"],                     "party": ["couple", "group"], "favorite": false, "enabled": false }
]
